rebugger/__init__.py
rebugger/_version.py
rebugger/perfetto.py
rebugger/rebugger.py
rebugger-0.3.dist-info/METADATA
rebugger-0.3.dist-info/WHEEL
rebugger-0.3.dist-info/top_level.txt
rebugger-0.3.dist-info/RECORD
